crash_ipdb/__init__.py
crash_ipdb-0.0.4.dist-info/METADATA
crash_ipdb-0.0.4.dist-info/WHEEL
crash_ipdb-0.0.4.dist-info/top_level.txt
crash_ipdb-0.0.4.dist-info/RECORD
