Metadata-Version: 2.1
Name: crash-ipdb
Version: 0.0.4
Summary: Trigger ipdb whenever Python crashes
Home-page: https://github.com/kwang2049/crash-ipdb
Author: Kexin Wang
Author-email: kexin.wang.2049@gmail.com
Project-URL: Bug Tracker, https://github.com/kwang2049/crash-ipdb/issues
Classifier: Programming Language :: Python :: 3
Classifier: License :: OSI Approved :: Apache Software License
Classifier: Operating System :: OS Independent
Requires-Python: >=3.6
Requires-Dist: ipython (==7.34)
